analysis.py
design.py
doe_class.py
designofexperiment-1.6.2.dist-info/LICENSE.txt
designofexperiment-1.6.2.dist-info/METADATA
designofexperiment-1.6.2.dist-info/WHEEL
designofexperiment-1.6.2.dist-info/top_level.txt
designofexperiment-1.6.2.dist-info/RECORD
