Metadata-Version: 2.1
Name: designofexperiment
Version: 1.6.2
Summary: A Python Package for intuitive design of experiments with user-friendly analysis of results
Home-page: https://github.com/JamesMarshall31/design-of-experiments
Author: James Marshall, Benedict Carling
Author-email: jm7618@ic.ac.uk, bencarling1@gmail.com
License: UNKNOWN
Platform: UNKNOWN
Classifier: Programming Language :: Python :: 3
Classifier: Programming Language :: Python :: 3.6
Classifier: Programming Language :: Python :: 3.7
Classifier: Programming Language :: Python :: 3.8
Classifier: License :: OSI Approved :: MIT License
Classifier: Natural Language :: English
Classifier: Operating System :: OS Independent
Requires-Dist: numpy (==1.19.1)
Requires-Dist: pandas (==1.1.1)
Provides-Extra: dev
Requires-Dist: pytest (>=6.0.1) ; extra == 'dev'
Requires-Dist: check-manifest (>=0.42) ; extra == 'dev'
Requires-Dist: twine (>=3.2.0) ; extra == 'dev'
